LICENSE
README.md
files/email.json
pyphisher.py
pyphisher-2.1.6.dist-info/LICENSE
pyphisher-2.1.6.dist-info/METADATA
pyphisher-2.1.6.dist-info/WHEEL
pyphisher-2.1.6.dist-info/entry_points.txt
pyphisher-2.1.6.dist-info/RECORD
